psqache/__init__.py
psqache/abcs.py
psqache/config.py
psqache/queries.py
psqache/queries.sql
psqache-0.3.0.dist-info/LICENSE
psqache-0.3.0.dist-info/METADATA
psqache-0.3.0.dist-info/WHEEL
psqache-0.3.0.dist-info/RECORD
