Metadata-Version: 2.1
Name: psqache
Version: 0.3.0
Summary: Fast Caching Library For Python/asyncio
Home-page: https://github.com/midnight-train/python-cache
Author: Adriano Mochama
Author-email: adriano@ibuqa.io
Requires-Python: >=3.12,<4.0
Classifier: Programming Language :: Python :: 3
Classifier: Programming Language :: Python :: 3.12
Classifier: Programming Language :: Python :: 3.13
Requires-Dist: aiosql (>=12.2,<13.0)
